.editorconfig
.gitignore
.travis.yml
AUTHORS.rst
CONTRIBUTING.rst
HISTORY.rst
LICENSE
MANIFEST.in
Makefile
README.rst
requirements_dev.txt
setup.py
tox.ini
.github/ISSUE_TEMPLATE.md
.idea/.gitignore
.idea/misc.xml
.idea/modules.xml
.idea/pyvkb.iml
.idea/vcs.xml
.idea/inspectionProfiles/Project_Default.xml
.idea/inspectionProfiles/profiles_settings.xml
docs/Makefile
docs/authors.rst
docs/conf.py
docs/contributing.rst
docs/history.rst
docs/index.rst
docs/installation.rst
docs/make.bat
docs/modules.rst
docs/readme.rst
docs/usage.rst
docs/vkb.cli.commands.rst
docs/vkb.cli.rst
docs/vkb.devices.rst
docs/vkb.led.rst
docs/vkb.rst
docs/_build/html/_static/file.png
docs/_build/html/_static/minus.png
docs/_build/html/_static/plus.png
pyvkb.egg-info/PKG-INFO
pyvkb.egg-info/SOURCES.txt
pyvkb.egg-info/dependency_links.txt
pyvkb.egg-info/entry_points.txt
pyvkb.egg-info/not-zip-safe
pyvkb.egg-info/requires.txt
pyvkb.egg-info/top_level.txt
tests/__init__.py
tests/test_pyvkb.py
vkb/__init__.py
vkb/_version.py
vkb/cli/__init__.py
vkb/cli/commands/__init__.py
vkb/cli/commands/general.py
vkb/cli/commands/led.py
vkb/devices/__init__.py
vkb/devices/base.py
vkb/devices/gladiatork.py
vkb/led/__init__.py
vkb/led/effects.py