Metadata-Version: 1.2
Name: pyvkb
Version: 0.1.0
Summary: Python library for controlling VKB devices
Home-page: https://github.com/ventrovar/pyvkb
Author: Ventorvar
Author-email: ventorvar@gmail.com
License: MIT license
Keywords: pyvkb
Platform: UNKNOWN
Classifier: Development Status :: 2 - Pre-Alpha
Classifier: Intended Audience :: Developers
Classifier: License :: OSI Approved :: MIT License
Classifier: Natural Language :: English
Classifier: Programming Language :: Python :: 3
Classifier: Programming Language :: Python :: 3.6
Classifier: Programming Language :: Python :: 3.7
Classifier: Programming Language :: Python :: 3.8
Requires-Python: >=3.5
